{
"type": "FeatureCollection",
"name": "poultry",
"crs": { "type": "name", "properties": { "name": "urn:ogc:def:crs:OGC:1.3:CRS84" } },
"features": [
{ "type": "Feature", "properties": { "Latitude": -18.56805556, "Longitude": 27.01666667, "Name": "SDC", "Type": "Poultry", "Picture": ".\/resources\/images\/Poultry\/SDC.jpg", "Activity": "" }, "geometry": { "type": "Point", "coordinates": [ 27.023573607256569, -18.56482976409437 ] } },
{ "type": "Feature", "properties": { "Latitude": 0.0, "Longitude": 0.0, "Name": "Chiguswi Support Group", "Type": "Poultry", "Picture": ".\/resources\/images\/Poultry\/Chiguswi.jpg", "Activity": "" }, "geometry": { "type": "Point", "coordinates": [ 27.036710588508356, -18.529240654587163 ] } },
{ "type": "Feature", "properties": { "Latitude": 0.0, "Longitude": 0.0, "Name": "Ukuthula Support Group", "Type": "Poultry", "Picture": ".\/resources\/images\/Poultry\/Ukuthula.jpg", "Activity": "" }, "geometry": { "type": "Point", "coordinates": [ 26.999630030791209, -18.552645763010673 ] } },
{ "type": "Feature", "properties": { "Latitude": 0.0, "Longitude": 0.0, "Name": "Simunye Support Group", "Type": "Poultry", "Picture": ".\/resources\/images\/Poultry\/SimunyeSG.jpg", "Activity": "Sabona has established the Simunye Support Group aimed at empowering members of the community living with HIV by providing them with the tools and resources to generate their own income through poultry rearing. This initiative not only fosters self-sufficiency but also enables participants to cover essential expenses such as food and medication. By promoting sustainable livelihoods, Sabona is helping to create a supportive environment where individuals can thrive and improve their quality of life." }, "geometry": { "type": "Point", "coordinates": [ 27.032021, -18.561318 ] } }
]
}
